[
  {
    "ID": 1,
    "CustomerName": "John Doe",
    "Email": "john.doe@example.com",
    "Phone": "1234567890",
    "Birthdate": "1980-01-01T00:00:00.000Z",
    "OrderDate": "2023-10-01T00:00:00.000Z",
    "Room": "101"
  },
  {
    "ID": 2,
    "CustomerName": "Jane Smith",
    "Email": "jane.smith@example.com",
    "Phone": "0987654321",
    "Birthdate": "1990-02-02T00:00:00.000Z",
    "OrderDate": "2023-10-02T00:00:00.000Z",
    "Room": "102"
  },
  {
    "ID": 3,
    "CustomerName": "Alice Johnson",
    "Email": "alice.johnson@example.com",
    "Phone": "1122334455",
    "Birthdate": "1985-03-03T00:00:00.000Z",
    "OrderDate": "2023-10-03T00:00:00.000Z",
    "Room": "103"
  },
  {
    "ID": 4,
    "CustomerName": "Bob Brown",
    "Email": "bob.brown@example.com",
    "Phone": "2233445566",
    "Birthdate": "1975-04-04T00:00:00.000Z",
    "OrderDate": "2023-10-04T00:00:00.000Z",
    "Room": "104"
  },
  {
    "ID": 5,
    "CustomerName": "Charlie Davis",
    "Email": "charlie.davis@example.com",
    "Phone": "3344556677",
    "Birthdate": "1995-05-05T00:00:00.000Z",
    "OrderDate": "2023-10-05T00:00:00.000Z",
    "Room": "105"
  },
  {
    "ID": 6,
    "CustomerName": "Diana Evans",
    "Email": "diana.evans@example.com",
    "Phone": "4455667788",
    "Birthdate": "1988-06-06T00:00:00.000Z",
    "OrderDate": "2023-10-06T00:00:00.000Z",
    "Room": "106"
  },
  {
    "ID": 7,
    "CustomerName": "Eve Foster",
    "Email": "eve.foster@example.com",
    "Phone": "5566778899",
    "Birthdate": "1992-07-07T00:00:00.000Z",
    "OrderDate": "2023-10-07T00:00:00.000Z",
    "Room": "107"
  },
  {
    "ID": 8,
    "CustomerName": "Frank Green",
    "Email": "frank.green@example.com",
    "Phone": "6677889900",
    "Birthdate": "1983-08-08T00:00:00.000Z",
    "OrderDate": "2023-10-08T00:00:00.000Z",
    "Room": "108"
  },
  {
    "ID": 9,
    "CustomerName": "Grace Harris",
    "Email": "grace.harris@example.com",
    "Phone": "7788990011",
    "Birthdate": "1978-09-09T00:00:00.000Z",
    "OrderDate": "2023-10-09T00:00:00.000Z",
    "Room": "109"
  },
  {
    "ID": 10,
    "CustomerName": "Hank Irving",
    "Email": "hank.irving@example.com",
    "Phone": "8899001122",
    "Birthdate": "1998-10-10T00:00:00.000Z",
    "OrderDate": "2023-10-10T00:00:00.000Z",
    "Room": "110"
  }
]